setup.py
Mezzanine_Widgets.egg-info/PKG-INFO
Mezzanine_Widgets.egg-info/SOURCES.txt
Mezzanine_Widgets.egg-info/dependency_links.txt
Mezzanine_Widgets.egg-info/not-zip-safe
Mezzanine_Widgets.egg-info/requires.txt
Mezzanine_Widgets.egg-info/top_level.txt
example/widgets/__init__.py
example/widgets/models.py
example/widgets/page_widgets.py
widget/__init__.py
widget/admin.py
widget/fields.py
widget/forms.py
widget/models.py
widget/page_widgets.py
widget/tests.py
widget/urls.py
widget/utilities.py
widget/views.py
widget/widget_pool.py
widget/widget_renderer.py
widget/migrations/0001_initial.py
widget/migrations/0002_auto__add_field_widget_display_title.py
widget/migrations/0003_auto__add_field_widget_keywords_string__add_field_widget_slug__add_fie.py
widget/migrations/0004_auto__del_widget.py
widget/migrations/0005_auto__add_widget.py
widget/migrations/0006_auto__del_field_widget_short_url.py
widget/migrations/0007_auto__del_field_widgetslot__order.py
widget/migrations/0008_auto__add_field_widget_user.py
widget/migrations/0009_auto__add_field_widget_page.py
widget/migrations/0010_auto__add_field_widget_page_less__add_unique_widget_display_title.py
widget/migrations/0011_auto__chg_field_widget_page.py
widget/migrations/0012_auto__add_widgetmodel__del_field_widget_widget_module__add_field_widge.py
widget/migrations/0013_auto__add_widgetoptions__add_widgetoptionfield.py
widget/migrations/0015_auto__add_field_widgetoptions_user__add_field_widgetmodel_user.py
widget/migrations/0016_auto__del_widgetoptions__del_widgetoptionfield__add_widgetoptiongroup_.py
widget/migrations/0017_auto__chg_field_widget_widgetslot.py
widget/migrations/0018_auto__del_field_widgetoptionentry_option_group__add_field_widgetoption.py
widget/migrations/0019_auto__chg_field_widget_display_title__del_unique_widget_display_title_.py
widget/migrations/__init__.py
widget/templatetags/__init__.py
widget/templatetags/widget_tags.py