Metadata-Version: 1.0
Name: Mezzanine-Widgets
Version: 0.1.0dev
Summary: Makes it super easy to add extra content to mezzanine pages and also add extended functionality. Check out the example app.
Home-page: http://osiloke.blogspot.com
Author: Osiloke Emoekpere
Author-email: osi@progwbtech.com
License: BSD
Platform: UNKNOWN
Classifier: Development Status :: 3 - Alpha
Classifier: Environment :: Web Environment
Classifier: Framework :: Django
Classifier: Intended Audience :: Developers
Classifier: License :: OSI Approved :: BSD License
Classifier: Operating System :: OS Independent
Classifier: Programming Language :: Python
Classifier: Topic :: Internet :: WWW/HTTP :: Dynamic Content
Classifier: Topic :: Software Development
Classifier: Topic :: Software Development :: Libraries :: Application Frameworks
